huanzhi_utils/__init__.py
huanzhi_utils/gorilla.py
huanzhi_utils-0.1.3.dist-info/licenses/LICENSE
huanzhi_utils-0.1.3.dist-info/METADATA
huanzhi_utils-0.1.3.dist-info/WHEEL
huanzhi_utils-0.1.3.dist-info/top_level.txt
huanzhi_utils-0.1.3.dist-info/RECORD
