Metadata-Version: 2.4
Name: huanzhi_utils
Version: 0.1.3
Summary: Handy utils library for Huanzhi Mao
Author-email: Huanzhi Mao <huanzhimao@eecs.berkeley.edu>
License: MIT License
Project-URL: Homepage, https://huanzhimao.com/
Requires-Python: >=3.10
License-File: LICENSE
Dynamic: license-file
